pigeoo/__init__.py
pigeoo/formatter.py
pigeoo/generator.py
pigeoo/main.py
pigeoo/parser.py
pigeoo/query.py
pigeoo/utils.py
pigeoo/static/style.css
pigeoo-0.0.4.0.dist-info/LICENSE
pigeoo-0.0.4.0.dist-info/METADATA
pigeoo-0.0.4.0.dist-info/WHEEL
pigeoo-0.0.4.0.dist-info/entry_points.txt
pigeoo-0.0.4.0.dist-info/top_level.txt
pigeoo-0.0.4.0.dist-info/RECORD
