Metadata-Version: 2.1
Name: pigeoo
Version: 0.0.4.0
Summary: Odoo Documentation Generator
Home-page: https://github.com/len-foss/pigeoo
Author: len-foss
Author-email: nans.lefebvre@acsone.eu
License: LGPLv3+
Project-URL: Bug Tracker, https://github.com/len-foss/pigeoo/issues
Platform: UNKNOWN
Classifier: Programming Language :: Python :: 3.8
Classifier: Intended Audience :: Developers
Classifier: License :: OSI Approved :: GNU Lesser General Public License v3 or later (LGPLv3+)
Classifier: Programming Language :: Python :: 3.8
Classifier: Framework :: Odoo
Requires-Python: >=3.8
License-File: LICENSE
Requires-Dist: click (>=7.1.2)
Requires-Dist: ConfigArgParse (>=1.3)
Requires-Dist: lxml (>=4.6.2)
